XPyLogger/__init__.py
XPyLogger/logs.py
XPyLogger-1.5.dist-info/METADATA
XPyLogger-1.5.dist-info/WHEEL
XPyLogger-1.5.dist-info/top_level.txt
XPyLogger-1.5.dist-info/RECORD
