Metadata-Version: 2.1
Name: XPyLogger
Version: 1.5
Summary: 一个开箱即用的 log 解决方案
Home-page: https://gitee.com/This-is-XiaoDeng/xpy-logger
Author: This is XiaoDeng
Author-email: 1744793737@qq.com
License: UNKNOWN
Platform: UNKNOWN
Classifier: Programming Language :: Python :: 3
Classifier: License :: OSI Approved :: MIT License
Classifier: Operating System :: OS Independent
Requires-Python: >=3.9
Requires-Dist: rich (>=12.0.1)
